hunabku_dspace/__init__.py
hunabku_dspace/_version.py
hunabku_dspace/endpoints/DSpace.py
Hunabku_dspace-0.0.3.dist-info/METADATA
Hunabku_dspace-0.0.3.dist-info/WHEEL
Hunabku_dspace-0.0.3.dist-info/top_level.txt
Hunabku_dspace-0.0.3.dist-info/RECORD
